area42/__init__.py
area42/hello_world.py
area42-0.0.1.dist-info/LICENSE
area42-0.0.1.dist-info/METADATA
area42-0.0.1.dist-info/WHEEL
area42-0.0.1.dist-info/top_level.txt
area42-0.0.1.dist-info/RECORD
